[
    {
        "title": "Изделия из клееного профилированного бруса (сосна) до 12 000 м",
        "type": "м3"
    },
    {
        "title": "Изделия из клееного профилированного бруса сечением 120х185 мм (сосна) до 12 000 м",
        "type": "м3"
    },
    {
        "title": "Изделия из клееного профилированного бруса сечением 160х185 мм (сосна) до 12 000 м",
        "type": "м3"
    },
    {
        "title": "Изделия из клееного профилированного бруса сечением 200х185 мм (сосна) до 12 000 м",
        "type": "м3"
    },
    {
        "title": "Изделия из клееного профилированного бруса сечением 240х185 мм (сосна) до 12 000 м",
        "type": "м3"
    },
    {
        "title": "Изделия из клееного профилированного бруса сечением 120х185 мм (сосна) до 6 000 м ЦЕЛЬНОЛАМЕЛЬНЫЙ",
        "type": "м3"
    },
    {
        "title": "Изделия из клееного профилированного бруса сечением 160х185 мм (сосна) до 6 000 м ЦЕЛЬНОЛАМЕЛЬНЫЙ",
        "type": "м3"
    },
    {
        "title": "Изделия из клееного профилированного бруса сечением 200х185 мм  (сосна) до 6 000 м ЦЕЛЬНОЛАМЕЛЬНЫЙ",
        "type": "м3"
    },
    {
        "title": "Изделия из клееного профилированного бруса сечением 240х185 мм (сосна) до 6 000 м ЦЕЛЬНОЛАМЕЛЬНЫЙ",
        "type": "м3"
    },
    {
        "title": "Изделия из клееного профилированного бруса (сосна) до 6 000 м ЦЕЛЬНОЛАМЕЛЬНЫЙ",
        "type": "м3"
    },
    {
        "title": "Оцилиндрованное бревно естественной влажности (сосна) диаметром 180 мм",
        "type": "м3"
    },
    {
        "title": "Оцилиндрованное бревно естественной влажности (сосна) диаметром 200 мм",
        "type": "м3"
    },
    {
        "title": "Оцилиндрованное бревно естественной влажности (сосна) диаметром 220 мм",
        "type": "м3"
    },
    {
        "title": "Оцилиндрованное бревно естественной влажности (сосна) диаметром 240 мм",
        "type": "м3"
    },
    {
        "title": "Оцилиндрованное бревно естественной влажности (сосна) диаметром 260 мм",
        "type": "м3"
    },
    {
        "title": "Оцилиндрованное бревно естественной влажности (сосна) диаметром 280 мм",
        "type": "м3"
    },
    {
        "title": "Брус клееный 200х180х12000 мм (сосна)",
        "type": "м3"
    },
    {
        "title": "Брус клееный 180х120х12000 мм (сосна)",
        "type": "м3"
    },
    {
        "title": "Столб из клееного бруса 120х120 мм (сосна) до 12000 мм",
        "type": "м3"
    },
    {
        "title": "Столб из клееного бруса 160х160 мм (сосна) до 12000 мм",
        "type": "м3"
    },
    {
        "title": "Столб из клееного бруса 180х180 мм (сосна) до 12000 мм",
        "type": "м3"
    },
    {
        "title": "Брус профилированный 194х145 мм до 6 000 мм естественная влажность",
        "type": "м3"
    },
    {
        "title": "Брус профилированный 145х145 мм до 6 000 мм естественная влажность",
        "type": "м3"
    },
    {
        "title": "Джут шир. 120 мм, толщ. 6 мм, рул. 20 м.п.",
        "type": "рул."
    },
    {
        "title": "Политерм 5мм ",
        "type": "м.п."
    },
    {
        "title": "Шкант, диаметр 25 мм, длина 1200 мм (береза)",
        "type": "шт."
    },
    {
        "title": "Упаковка в пленку",
        "type": "м3"
    },
    {
        "title": "Сверловка каналов под скрытую электропроводку",
        "type": "м3"
    },
    {
        "title": "Нарезка пазов для оконной и дверной фальш-коробки",
        "type": "м.п."
    },
    {
        "title": "Опора бруса 50 мм",
        "type": "шт."
    },
    {
        "title": "Опора бруса 120 мм",
        "type": "шт."
    },
    {
        "title": "Пружинный узел Сила",
        "type": "шт."
    },
    {
        "title": "Разработка документации для производства и сборки",
        "type": "м3"
    },
    {
        "title": "Брус (сосна) 200х200 до 6000мм  естественная влажность",
        "type": "м3"
    },
    {
        "title": "Брус (сосна) 200х150 до 6000мм  естественная влажность",
        "type": "м3"
    },
    {
        "title": "Брус (сосна) 100х200 до 6000 мм естественная влажность",
        "type": "м3"
    },
    {
        "title": "Анкер регулировочный по высоте",
        "type": "шт."
    },
    {
        "title": "Шуруп под головку 8х80 (глухарь)",
        "type": "шт."
    },
    {
        "title": "Пластина гвоздевая 100х200 мм",
        "type": "шт."
    },
    {
        "title": "Пластина перфорированная 50х100 мм",
        "type": "шт."
    },
    {
        "title": "Скоба строительная 8х200х60",
        "type": "пачка"
    },
    {
        "title": "Отсечная гидроизоляция Технониколь 0,4х20 м",
        "type": "рул."
    },
    {
        "title": "Саморезы 5,0х50 потай, ж/у ",
        "type": "шт."
    },
    {
        "title": "Шуруп для перфорированного крепежа 5х50 мм, полусферическая головка",
        "type": "шт."
    },
    {
        "title": "Гвозди, саморезы, скобы для степлера",
        "type": "комплект"
    },
    {
        "title": "Брусок 50х50х6000 мм (сосна) естественная влажность",
        "type": "м3"
    },
    {
        "title": "Металлочерепица Монтеррей. 0,5",
        "type": "м2"
    },
    {
        "title": "Металлочерепица Монтеррей. 0,45",
        "type": "м2"
    },
    {
        "title": "Конек плоский, 2 м",
        "type": "шт."
    },
    {
        "title": "Уплотнитель универсальный, 2 м",
        "type": "шт."
    },
    {
        "title": "Упаковка металлочерепицы",
        "type": "усл."
    },
    {
        "title": "Ветровая планка, 2 м",
        "type": "шт."
    },
    {
        "title": "Карнизная планка, 2 м",
        "type": "шт."
    },
    {
        "title": "Планка примыкания верхняя, 2 м ",
        "type": "шт."
    },
    {
        "title": "Планка примыкания нижняя, 2 м",
        "type": "шт."
    },
    {
        "title": "Изоспан AS, 75 м2",
        "type": "рул."
    },
    {
        "title": "Изоспан DM 75 м2",
        "type": "рул."
    },
    {
        "title": "Изоспан A цоколь",
        "type": "рул."
    },
    {
        "title": "Кровельный проходной элемент",
        "type": "шт."
    },
    {
        "title": "Пена монтажная",
        "type": "бал"
    },
    {
        "title": "Изоспан ML Proff, 25 м.п.",
        "type": "рул."
    },
    {
        "title": "Изоспан KL+, 25 м.п.",
        "type": "рул."
    },
    {
        "title": "Лента изоляционная Паранет 20м",
        "type": "шт."
    },
    {
        "title": "Скользящая опора стропил",
        "type": "шт."
    },
    {
        "title": "Доска антисептированная 200х50х6000 мм (сосна) камерная сушка",
        "type": "м3"
    },
    {
        "title": "Доска антисептированная 100х25х6000 мм (сосна) камерная сушка",
        "type": "м3"
    },
    {
        "title": "Брусок антисептированный 50х50х6000 мм (сосна) камерная сушка",
        "type": "м3"
    },
    {
        "title": "Технологический запас древесины (естественная влажность)",
        "type": "м3"
    },
    {
        "title": "Фанера нешлиф. 1525х1525х12 мм",
        "type": "шт."
    },
    {
        "title": "Фанера нешлиф. 1525х1525х10 мм",
        "type": "шт."
    },
    {
        "title": "ЦСП 16 мм 1250х3200 мм",
        "type": "шт."
    },
    {
        "title": "Обсадная коробка для дверных проемов 120,160, 200 мм, Т-образная, сорт АБ, толщина 40 мм без порога",
        "type": "м.п."
    },
    {
        "title": "Обсадная коробка для оконных проемов 120, 160, 200 мм, Т-образная, сорт АБ, толщина 40 мм без подоконника",
        "type": "м.п."
    },
    {
        "title": "Входная дверь с терморазрывом (эконом)",
        "type": "шт."
    },
    {
        "title": "Лента герметизирующая внутренняя, 7 м",
        "type": "рул."
    },
    {
        "title": "Лента герметизирующая Технониколь наружная  3 м",
        "type": "рул."
    },
    {
        "title": "Доска антисептированная 100х50х6000 мм (сосна) камерная сушка",
        "type": "м3"
    },
    {
        "title": "Доска террасная лиственница гладкая",
        "type": "м.п."
    },
    {
        "title": "Скрытый крепеж для террасной доски (твин)",
        "type": "шт."
    },
    {
        "title": "Планкен прямой (сосна) сорт АВ",
        "type": "м.п."
    },
    {
        "title": "Крепеж для планкена",
        "type": "шт."
    },
    {
        "title": "Водосборная воронка Docke Premium",
        "type": "шт."
    },
    {
        "title": "Желоб водосточный  3000 мм  Docke Premium",
        "type": "шт."
    },
    {
        "title": "Соединитель желобов Docke Premium",
        "type": "шт."
    },
    {
        "title": "Заглушка желоба Docke Premium",
        "type": "шт."
    },
    {
        "title": "Кронштейна желоба Docke Premium",
        "type": "шт."
    },
    {
        "title": "Колено трубы 45 град. Docke Premium",
        "type": "шт."
    },
    {
        "title": "Наконечник Docke Premium",
        "type": "шт."
    },
    {
        "title": "Труба водосточная 3000 мм Docke Premium",
        "type": "шт."
    },
    {
        "title": "Труба водосточная 1000 мм Docke Premium",
        "type": "шт."
    },
    {
        "title": "Хомут универсальный Docke Premium",
        "type": "шт."
    },
    {
        "title": "Воронка желоба ТЕХНОНИКОЛЬ ПВХ 125/82",
        "type": "шт."
    },
    {
        "title": "Желоб водосточный ТЕХНОНИКОЛЬ ПВХ 125/82, 3 м",
        "type": "шт."
    },
    {
        "title": "Соединитель желоба ТЕХНОНИКОЛЬ ПВХ 125/82",
        "type": "шт."
    },
    {
        "title": "Заглушка желоба ТЕХНОНИКОЛЬ ПВХ 125/82",
        "type": "шт."
    },
    {
        "title": "Кронштейна желоба ТЕХНОНИКОЛЬ",
        "type": "шт."
    },
    {
        "title": "Колено трубы ТЕХНОНИКОЛЬ ПВХ 125/82",
        "type": "шт."
    },
    {
        "title": "Слив трубы ТЕХНОНИКОЛЬ ПВХ 125/82",
        "type": "шт."
    },
    {
        "title": "Труба водосточная ТЕХНОНИКОЛЬ ПВХ 125/82, 3 м",
        "type": "шт."
    },
    {
        "title": "Труба водосточная ТЕХНОНИКОЛЬ ПВХ 125/82, 1 м",
        "type": "шт."
    },
    {
        "title": "Хомут трубы универсальный ТЕХНОНИКОЛЬ ПВХ 125/82",
        "type": "шт."
    },
    {
        "title": "Виниловый сайдинг",
        "type": "м2"
    },
    {
        "title": "Планка соединительная",
        "type": "м.п."
    },
    {
        "title": "Угол наружный 90 гр",
        "type": "м.п."
    },
    {
        "title": "Вагонка штиль 16х115 мм на стены  (сосна)",
        "type": "м2"
    },
    {
        "title": "Универсальный бесцветный антисептик neomid 440 eco, 5 л",
        "type": "шт."
    },
    {
        "title": "Ламинат 32 класс, 8 мм",
        "type": "м2"
    },
    {
        "title": "Балясина 50х50 1с.",
        "type": "шт"
    },
    {
        "title": "Поручень 65х3000мм",
        "type": "шт"
    },
    {
        "title": "Наличник 18х130х6000 мм (сосна) Экстра",
        "type": "м.п."
    },
    {
        "title": "Наличник 12х120х2200 мм (сосна)",
        "type": "м.п."
    },
    {
        "title": "Брусок 50х50х6000 мм (сосна) камерная сушка",
        "type": "м3"
    },
    {
        "title": "Угловой желоб 90 градусов ",
        "type": "шт."
    },
    {
        "title": "Монолитный поликарбонат прозрачный 4 мм 2050х3050 мм",
        "type": "шт."
    },
    {
        "title": "Профиль соединительный",
        "type": "шт."
    },
    {
        "title": "Заглушка торцевая",
        "type": "шт."
    },
    {
        "title": "Лента герметизирующая Изобонд 38 мм х 25м",
        "type": "шт."
    },
    {
        "title": "Брусок 40х40х6000 мм (сосна) камерная сушка",
        "type": "м.п."
    },
    {
        "title": "Фанера 1220х2440х20 мм",
        "type": "лист"
    },
    {
        "title": "Шкант 25х25х1000 мм естеств. влажности (сосна)",
        "type": "шт."
    },
    {
        "title": "Доска естественной влажности 200х50х6000 мм (сосна)",
        "type": "м3"
    },
    {
        "title": "Доска естественной влажности 150х50х6000 мм (сосна)",
        "type": "м3"
    },
    {
        "title": "Доска естественной влажности 100х25х6000 мм (сосна)",
        "type": "м3"
    },
    {
        "title": "Столб профилированный 145х145 мм (сосна) до 6000 мм камерная сушка",
        "type": "м3"
    },
    {
        "title": "Полнотелый кирпич керамический 250х120х65мм ",
        "type": "шт."
    },
    {
        "title": "Уголок крепежный усиленный 150х150 мм ",
        "type": "шт."
    },
    {
        "title": "Профиль направляющий Кнауф 50х40 мм",
        "type": "шт."
    },
    {
        "title": "Гипсокартон Кнауф влагостойкий 2500х1200х12,5 мм",
        "type": ""
    },
    {
        "title": "OSB-3 (ОСБ-3) 12 мм 1250х2500 мм",
        "type": "шт."
    },
    {
        "title": "Профиль стоечный Кнауф 50х50 мм",
        "type": "шт."
    },
    {
        "title": "Столб профилированный 194х194 мм (сосна) до 6000 мм камерная сушка",
        "type": "м3"
    },
    {
        "title": "Брус профилированный 145х145 мм камерная сушка",
        "type": "м3"
    },
    {
        "title": "Брус профилированный 194х145 мм камерная сушка",
        "type": "м3"
    },
    {
        "title": "Кирпич одинарный полнотелый 250х120х65мм ",
        "type": "шт."
    },
    {
        "title": "Кладочная ЦПС М150 (25кг)",
        "type": "меш."
    },
    {
        "title": "Кладочная сетка 2*0,51м  (50х50х2.5мм)",
        "type": "шт."
    },
    {
        "title": "Метизы для домокомплекта",
        "type": "к-т"
    },
    {
        "title": "Метизы для кровли",
        "type": "к-т"
    },
    {
        "title": "Метизы и расходные материалы",
        "type": "к-т"
    },
    {
        "title": "Окно деревянное в парную",
        "type": "шт."
    },
    {
        "title": "Окно профиль Проплекс Оптима 58 мм 3 кам. 13 сис., заполнение 4_10_4_10_4, цвет белый",
        "type": "м2"
    },
    {
        "title": "Скоба строительная 8х200х60",
        "type": "шт."
    },
    {
        "title": "Металлическая сварная сетка от грызунов 6х6мм, рулон 15 кв.м., в т.ч. гвозди, доставка",
        "type": "рул."
    },
    {
        "title": "Джут 5х200 мм",
        "type": "м.п."
    },
    {
        "title": "Доска 150х50х6000 мм (сосна) камерная сушка",
        "type": "м3"
    },
    {
        "title": "Доска 200х50х6000 мм (сосна) камерная сушка",
        "type": "м3"
    },
    {
        "title": "Доска 100х40х6000 мм (сосна) камерная сушка ",
        "type": "м3"
    },
    {
        "title": "Доска 100х50х6000 мм (сосна) камерная сушка ",
        "type": "м3"
    },
    {
        "title": "Доска 100х25х6000 мм (сосна) камерная сушка",
        "type": "м3"
    },
    {
        "title": "Утеплитель Кнауф 0,6 м3 (толщиной 100 мм) коэффициент теплопроводности 0,037",
        "type": "упак."
    },
    {
        "title": "Утеплитель Кнауф 0,6 м3 (толщиной 50 мм) коэффициент теплопроводности 0,037",
        "type": "упак."
    },
    {
        "title": "Гипсокартон Кнауф влагостойкий 2500х1200x12,5 мм",
        "type": "шт."
    },
    {
        "title": "Планка ендовы верхняя, 2м",
        "type": "шт."
    },
    {
        "title": "Планка ендовы нижняя, 2м",
        "type": "шт."
    },
    {
        "title": "Уголок усиленный 95х95х65 мм",
        "type": "шт."
    },
    {
        "title": "Технологический запас древесины (сухой пилмат)",
        "type": "комплект"
    },
    {
        "title": "Доска 200х50х6000 мм (сосна) камерная сушка ",
        "type": "м3"
    },
    {
        "title": "Откосы (металл)",
        "type": "м.п."
    },
    {
        "title": "Подоконник ПВХ",
        "type": "м.п."
    },
    {
        "title": "ПВХ МЕМБРАНА LOGICROOF V-RP, 1,5 ММ (2,10X10 М), ТЕМНО-СЕРАЯ",
        "type": "рул."
    },
    {
        "title": "Круглый тарельчатый держатель ТЕХНОНИКОЛЬ 50мм",
        "type": "упак."
    },
    {
        "title": "Геотекстиль термообработанный 300 г/м² 2Х50М",
        "type": "рул."
    },
    {
        "title": "OSB-3 18 мм 1250х2500 мм",
        "type": "шт."
    },
    {
        "title": "КЛЕЙ ТЕХНОНИКОЛЬ 508 PROFESSIONAL, 1000 МЛ, ШТ.",
        "type": "шт."
    },
    {
        "title": "ЛЕНТА УПЛОТНИТЕЛЬНАЯ САМОКЛЕЯЩАЯСЯ ТЕХНОНИКОЛЬ АЛЬФА КОНТРБРУС 60 ММ*30 М",
        "type": "шт."
    },
    {
        "title": "ТЕХНОНИКОЛЬ АЛЬФА ТОП (1,5 X 50 М)",
        "type": "рул."
    },
    {
        "title": "Фартук металлический для парапета, 2 м",
        "type": "шт."
    },
    {
        "title": "Фасонный элемент угловой, 2 м",
        "type": "шт."
    },
    {
        "title": "РЕЙКА КРАЕВАЯ АЛЮМИНИЕВАЯ ТЕХНОНИКОЛЬ 2,0 М (100 П.М./УПАК)",
        "type": "упак."
    },
    {
        "title": "Окно профиль Arctica_exprof, фурнитура siegenia classic, заполнение 4_14_4_14_4, стекло энерго, цвет белый",
        "type": "м2"
    },
    {
        "title": "Розетки, выключатели",
        "type": "шт."
    },
    {
        "title": "Черепица (двухслойная) Shinglas Ранчо (упаковка 2 м2)",
        "type": "упак."
    },
    {
        "title": "Коньково-карнизная черепица Shinglas Ранчо",
        "type": "упак."
    },
    {
        "title": "Подкладочный ковер Andeper prof, рул.40м2",
        "type": "рул."
    },
    {
        "title": "Подкладочный ковер Andeper ultra, рул.15м2",
        "type": "рул."
    },
    {
        "title": "Мастика для гибкой черепицы Технониколь №23 (Фиксер), 12 кг.",
        "type": "ведро"
    },
    {
        "title": "ОСП-3, 9мм",
        "type": "лист"
    },
    {
        "title": "Ендовый ковер (10м2)",
        "type": "рул."
    },
    {
        "title": "Коньковый аэратор ТехноНИКОЛЬ, шт .",
        "type": "шт."
    }
]